cbar/__init__.py
cbar/core.py
cbar_rates-1.3.0.dist-info/LICENSE.md
cbar_rates-1.3.0.dist-info/METADATA
cbar_rates-1.3.0.dist-info/WHEEL
cbar_rates-1.3.0.dist-info/top_level.txt
cbar_rates-1.3.0.dist-info/RECORD
