Metadata-Version: 2.1
Name: cbar-rates
Version: 1.3.0
Summary: Python library to work with AZN (Azerbaijani manat) official rates
Author-email: Tahir Jalilov <tahir.jalilov@gmail.com>
Project-URL: Homepage, https://github.com/TahirJalilov/cbar-rates/
Project-URL: Repository, https://github.com/TahirJalilov/cbar-rates/
Project-URL: Issues, https://github.com/TahirJalilov/cbar-rates/issues
Project-URL: Changelog, https://github.com/TahirJalilov/cbar-rates/blob/main/CHANGES.md
Keywords: cbar-rates,AZN,Azerbaijan,AZN-Rates,CBAR,Manat,Mezenne
Classifier: Development Status :: 5 - Production/Stable
Classifier: Intended Audience :: Developers
Classifier: Intended Audience :: Information Technology
Classifier: License :: OSI Approved :: MIT License
Classifier: Operating System :: OS Independent
Classifier: Programming Language :: Python
Classifier: Programming Language :: Python :: 3
Classifier: Programming Language :: Python :: 3.7
Classifier: Programming Language :: Python :: 3.8
Classifier: Programming Language :: Python :: 3.9
Classifier: Programming Language :: Python :: 3.10
Classifier: Programming Language :: Python :: 3.11
Classifier: Programming Language :: Python :: 3.12
Classifier: Programming Language :: Python :: 3.13
Classifier: Programming Language :: Python :: Implementation :: CPython
Classifier: Programming Language :: Python :: Implementation :: PyPy
Classifier: Topic :: Internet :: WWW/HTTP :: Dynamic Content
Classifier: Topic :: Software Development :: Libraries :: Python Modules
Classifier: Typing :: Typed
Requires-Python: >=3.7
License-File: LICENSE.md
Requires-Dist: typing_extensions>=4.7.0; python_version < "3.9"
Requires-Dist: requests>=2.20.0
Provides-Extra: dev
Requires-Dist: pytest>=7.4.4; extra == "dev"
